world_nbdev/__init__.py
world_nbdev/_nbdev.py
world_nbdev/core.py
world_nbdev-0.0.1.dist-info/LICENSE
world_nbdev-0.0.1.dist-info/METADATA
world_nbdev-0.0.1.dist-info/WHEEL
world_nbdev-0.0.1.dist-info/entry_points.txt
world_nbdev-0.0.1.dist-info/top_level.txt
world_nbdev-0.0.1.dist-info/RECORD
